kozmodb/__init__.py
kozmodb/client/__init__.py
kozmodb/client/main.py
kozmodb/configs/__init__.py
kozmodb/configs/base.py
kozmodb/configs/enums.py
kozmodb/configs/prompts.py
kozmodb/configs/embeddings/__init__.py
kozmodb/configs/embeddings/base.py
kozmodb/configs/llms/__init__.py
kozmodb/configs/llms/base.py
kozmodb/configs/vector_stores/__init__.py
kozmodb/configs/vector_stores/azure_ai_search.py
kozmodb/configs/vector_stores/chroma.py
kozmodb/configs/vector_stores/elasticsearch.py
kozmodb/configs/vector_stores/faiss.py
kozmodb/configs/vector_stores/langchain.py
kozmodb/configs/vector_stores/milvus.py
kozmodb/configs/vector_stores/opensearch.py
kozmodb/configs/vector_stores/pgvector.py
kozmodb/configs/vector_stores/pinecone.py
kozmodb/configs/vector_stores/qdrant.py
kozmodb/configs/vector_stores/redis.py
kozmodb/configs/vector_stores/supabase.py
kozmodb/configs/vector_stores/upstash_vector.py
kozmodb/configs/vector_stores/vertex_ai_vector_search.py
kozmodb/configs/vector_stores/weaviate.py
kozmodb/embeddings/__init__.py
kozmodb/embeddings/aws_bedrock.py
kozmodb/embeddings/azure_openai.py
kozmodb/embeddings/base.py
kozmodb/embeddings/configs.py
kozmodb/embeddings/gemini.py
kozmodb/embeddings/huggingface.py
kozmodb/embeddings/langchain.py
kozmodb/embeddings/lmstudio.py
kozmodb/embeddings/mock.py
kozmodb/embeddings/ollama.py
kozmodb/embeddings/openai.py
kozmodb/embeddings/together.py
kozmodb/embeddings/vertexai.py
kozmodb/graphs/configs.py
kozmodb/graphs/tools.py
kozmodb/graphs/utils.py
kozmodb/llms/__init__.py
kozmodb/llms/anthropic.py
kozmodb/llms/aws_bedrock.py
kozmodb/llms/azure_openai.py
kozmodb/llms/azure_openai_structured.py
kozmodb/llms/base.py
kozmodb/llms/configs.py
kozmodb/llms/deepseek.py
kozmodb/llms/gemini.py
kozmodb/llms/groq.py
kozmodb/llms/langchain.py
kozmodb/llms/litellm.py
kozmodb/llms/lmstudio.py
kozmodb/llms/ollama.py
kozmodb/llms/openai.py
kozmodb/llms/openai_structured.py
kozmodb/llms/sarvam.py
kozmodb/llms/together.py
kozmodb/llms/xai.py
kozmodb-0.1.102.dist-info/METADATA
kozmodb-0.1.102.dist-info/WHEEL
kozmodb-0.1.102.dist-info/licenses/LICENSE
kozmodb-0.1.102.dist-info/RECORD
