Metadata-Version: 2.4
Name: kozmodb
Version: 0.1.102
Summary: Long-term memory for AI Agents
Author-email: "Digitrans, Inc" <developers@digi-trans.org>
License-File: LICENSE
Requires-Python: <4.0,>=3.9
Requires-Dist: openai>=1.33.0
Requires-Dist: posthog>=3.5.0
Requires-Dist: pydantic>=2.7.3
Requires-Dist: pytz>=2024.1
Requires-Dist: qdrant-client>=1.9.1
Requires-Dist: sqlalchemy>=2.0.31
Provides-Extra: dev
Requires-Dist: isort>=5.13.2; extra == 'dev'
Requires-Dist: pytest>=8.2.2; extra == 'dev'
Requires-Dist: ruff>=0.6.5; extra == 'dev'
Provides-Extra: graph
Requires-Dist: langchain-neo4j>=0.4.0; extra == 'graph'
Requires-Dist: neo4j>=5.23.1; extra == 'graph'
Requires-Dist: rank-bm25>=0.2.2; extra == 'graph'
Provides-Extra: test
Requires-Dist: pytest-asyncio>=0.23.7; extra == 'test'
Requires-Dist: pytest-mock>=3.14.0; extra == 'test'
Requires-Dist: pytest>=8.2.2; extra == 'test'
